README.rst
setup.py
bin/psprofile
psprofile/__init__.py
psprofile/main.py
psprofile/util.py
psprofile.egg-info/PKG-INFO
psprofile.egg-info/SOURCES.txt
psprofile.egg-info/dependency_links.txt
psprofile.egg-info/requires.txt
psprofile.egg-info/top_level.txt