Metadata-Version: 1.0
Name: psprofile
Version: 0.1.10
Summary: Collects resource usage of an executed script
Home-page: http://github.com/egafni/PsProfile
Author: Erik Gafni
Author-email: egafni@gmail.com
License: GPL
Platform: UNKNOWN
